mypy_drf_plugin/__init__.py
mypy_drf_plugin/main.py
mypy_drf_plugin/lib/__init__.py
mypy_drf_plugin/lib/fullnames.py
mypy_drf_plugin/lib/helpers.py
mypy_drf_plugin/transformers/__init__.py
mypy_drf_plugin/transformers/serializers.py
rest_framework-stubs/__init__.pyi
rest_framework-stubs/apps.pyi
rest_framework-stubs/authentication.pyi
rest_framework-stubs/checks.pyi
rest_framework-stubs/compat.pyi
rest_framework-stubs/decorators.pyi
rest_framework-stubs/documentation.pyi
rest_framework-stubs/exceptions.pyi
rest_framework-stubs/fields.pyi
rest_framework-stubs/filters.pyi
rest_framework-stubs/generics.pyi
rest_framework-stubs/metadata.pyi
rest_framework-stubs/mixins.pyi
rest_framework-stubs/negotiation.pyi
rest_framework-stubs/pagination.pyi
rest_framework-stubs/parsers.pyi
rest_framework-stubs/permissions.pyi
rest_framework-stubs/relations.pyi
rest_framework-stubs/renderers.pyi
rest_framework-stubs/request.pyi
rest_framework-stubs/response.pyi
rest_framework-stubs/reverse.pyi
rest_framework-stubs/routers.pyi
rest_framework-stubs/serializers.pyi
rest_framework-stubs/settings.pyi
rest_framework-stubs/status.pyi
rest_framework-stubs/test.pyi
rest_framework-stubs/throttling.pyi
rest_framework-stubs/urlpatterns.pyi
rest_framework-stubs/urls.pyi
rest_framework-stubs/validators.pyi
rest_framework-stubs/versioning.pyi
rest_framework-stubs/views.pyi
rest_framework-stubs/viewsets.pyi
rest_framework-stubs/authtoken/__init__.pyi
rest_framework-stubs/authtoken/admin.pyi
rest_framework-stubs/authtoken/apps.pyi
rest_framework-stubs/authtoken/models.pyi
rest_framework-stubs/authtoken/serializers.pyi
rest_framework-stubs/authtoken/views.pyi
rest_framework-stubs/authtoken/management/__init__.pyi
rest_framework-stubs/authtoken/management/commands/__init__.pyi
rest_framework-stubs/authtoken/management/commands/drf_create_token.pyi
rest_framework-stubs/management/__init__.pyi
rest_framework-stubs/management/commands/__init__.pyi
sentry_forked_djangorestframework_stubs-3.16.3.post1.dist-info/licenses/LICENSE.txt
sentry_forked_djangorestframework_stubs-3.16.3.post1.dist-info/METADATA
sentry_forked_djangorestframework_stubs-3.16.3.post1.dist-info/WHEEL
sentry_forked_djangorestframework_stubs-3.16.3.post1.dist-info/top_level.txt
sentry_forked_djangorestframework_stubs-3.16.3.post1.dist-info/RECORD
